gilito/__init__.py
gilito/__main__.py
gilito/cli.py
gilito/models.py
gilito/typetools.py
gilito/plugins/__init__.py
gilito/plugins/bbva.py
gilito/plugins/categorize.py
gilito/plugins/csv.py
gilito/plugins/native.py
gilito/plugins/xlsx.py
gilito-0.0.1.dist-info/LICENSE
gilito-0.0.1.dist-info/METADATA
gilito-0.0.1.dist-info/WHEEL
gilito-0.0.1.dist-info/entry_points.txt
gilito-0.0.1.dist-info/top_level.txt
gilito-0.0.1.dist-info/RECORD
