Metadata-Version: 2.1
Name: gilito
Version: 0.0.1
Summary: Command line tool to manage your cash
Home-page: https://github.com/ldotlopez/gilito
Author: Luis López
Author-email: luis@cuarentaydos.com
License: UNKNOWN
Project-URL: Bug Tracker, https://github.com/ldotlopez/gilito/issues
Platform: UNKNOWN
Classifier: Programming Language :: Python :: 3
Classifier: License :: OSI Approved :: MIT License
Classifier: Operating System :: OS Independent
Requires-Python: >=3.9
License-File: LICENSE
Requires-Dist: click (==8.1.2)
Requires-Dist: pydantic (==1.9.0)
